pyauth0/__init__.py
pyauth0/errors.py
pyauth0/token_creator.py
pyauth0/token_provider.py
pyauth0/token_verifier.py
pyauth0/utils.py
pyauth0-0.2.0.dist-info/LICENSE
pyauth0-0.2.0.dist-info/METADATA
pyauth0-0.2.0.dist-info/WHEEL
pyauth0-0.2.0.dist-info/RECORD
