Metadata-Version: 2.1
Name: pyauth0
Version: 0.2.0
Summary: Python utilities for Auth0
Home-page: https://svaponi.github.io/pyauth0
License: MIT
Author: svaponi
Author-email: 10941963+svaponi@users.noreply.github.com
Requires-Python: >=3.8,<3.13
Classifier: Development Status :: 4 - Beta
Classifier: License :: OSI Approved :: MIT License
Classifier: Programming Language :: Python :: 3
Classifier: Programming Language :: Python :: 3.8
Classifier: Programming Language :: Python :: 3.9
Classifier: Programming Language :: Python :: 3.10
Classifier: Programming Language :: Python :: 3.11
Classifier: Programming Language :: Python :: 3.12
Provides-Extra: crypto
Requires-Dist: cryptography (>=42.0.6,<43.0.0) ; extra == "crypto"
Requires-Dist: httpx (>=0.27.0,<0.28.0)
Requires-Dist: python-jose (>=3.3.0,<4.0.0)
Project-URL: Repository, https://github.com/svaponi/pyauth0
